yaxi.py
yaxi-0.2.2.dist-info/LICENSE
yaxi-0.2.2.dist-info/WHEEL
yaxi-0.2.2.dist-info/METADATA
yaxi-0.2.2.dist-info/RECORD
